setup.py
django_tables2_simplefilter/__init__.py
django_tables2_simplefilter/views.py
django_tables2_simplefilter.egg-info/PKG-INFO
django_tables2_simplefilter.egg-info/SOURCES.txt
django_tables2_simplefilter.egg-info/dependency_links.txt
django_tables2_simplefilter.egg-info/not-zip-safe
django_tables2_simplefilter.egg-info/requires.txt
django_tables2_simplefilter.egg-info/top_level.txt