Metadata-Version: 1.1
Name: django-tables2-simplefilter
Version: 0.1
Summary: Simple filters for django-tables2
Home-page: https://github.com/mmilidoni/django-tables2-simplefilter
Author: Benjie Chen
Author-email: benjie@alum.mit.edu
License: UNKNOWN
Platform: UNKNOWN
Classifier: Environment :: Web Environment
Classifier: Framework :: Django
Classifier: Intended Audience :: Developers
Classifier: License :: OSI Approved :: BSD License
Classifier: Operating System :: OS Independent
Classifier: Programming Language :: Python
Classifier: Topic :: Internet :: WWW/HTTP
Classifier: Topic :: Software Development :: Libraries
